eiscp/__init__.py
eiscp/commands.py
eiscp/core.py
eiscp/script.py
eiscp/utils.py
dannytrigo_onkyo_eiscp-1.2.14.dist-info/LICENSE
dannytrigo_onkyo_eiscp-1.2.14.dist-info/METADATA
dannytrigo_onkyo_eiscp-1.2.14.dist-info/WHEEL
dannytrigo_onkyo_eiscp-1.2.14.dist-info/entry_points.txt
dannytrigo_onkyo_eiscp-1.2.14.dist-info/top_level.txt
dannytrigo_onkyo_eiscp-1.2.14.dist-info/RECORD
