Metadata-Version: 2.1
Name: dannytrigo-onkyo-eiscp
Version: 1.2.14
Summary: Control Onkyo receivers over ethernet. (dannytrigo fork for bugfix)
Home-page: https://github.com/dannytrigo/onkyo-eiscp
Author: Michael Elsdörfer
Author-email: michael@elsdoerfer.com
License: MIT
Platform: any
Classifier: Topic :: System :: Networking
Classifier: Topic :: Games/Entertainment
Classifier: Topic :: Multimedia
Classifier: Intended Audience :: Developers
Classifier: Intended Audience :: End Users/Desktop
Classifier: License :: OSI Approved :: MIT License
Classifier: Operating System :: OS Independent
Classifier: Programming Language :: Python
License-File: LICENSE
Requires-Dist: docopt >=0.4.1
Requires-Dist: netifaces
Requires-Dist: xmltodict >=0.12.0
